<top>
    <sensor>
        <touch name="finger1_sensor" site="finger1_surf"/>
        <touch name="finger2_sensor" site="finger2_surf"/>
        <framepos name="object0_sensor" objname="object0" objtype="body"/>
    </sensor>
    <worldbody>
        <body childclass="freejoint" name="object0" pos="0 0 0">
            <joint type="free"/>
            <geom conaffinity="7" contype="7" friction="1.0 0.1 0.02" mass="1" rgba="0.5609950869731065 0.5128530817807687 0.49918429999891445 1" size="0.02 0.07846917917940517 0.02" type="box"/>
            <geom conaffinity="7" contype="7" friction="1.0 0.1 0.02" mass="1" pos="0.07393964397701046 0.03807652284929687 0.0" rgba="0.40361062793033076 0.9824033875413372 0.5013392073619163 1" size="0.07393964397701046 0.02 0.02" type="box"/>
        </body>
    </worldbody>
</top>